{
    "baseline_testing_loss": {
        "criterion": "absolute_error",
        "max_depth": 161,
        "min_samples_split": 23,
        "min_samples_leaf": 1,
        "ccp_alpha": 0.0,
        "n_estimators": 114,
        "bootstrap": true,
        "max_samples": 0.52
    },
    "batch_normalisation_testing_loss": {
        "criterion": "friedman_mse",
        "max_depth": 298,
        "min_samples_split": 18,
        "min_samples_leaf": 8,
        "ccp_alpha": 0.0,
        "n_estimators": 79,
        "bootstrap": true,
        "max_samples": 0.84
    },
    "dropout_testing_loss": {
        "criterion": "poisson",
        "max_depth": 86,
        "min_samples_split": 7,
        "min_samples_leaf": 4,
        "ccp_alpha": 0.0,
        "n_estimators": 206,
        "bootstrap": true,
        "max_samples": 1.0
    },
    "layer_normalisation_testing_loss": {
        "criterion": "friedman_mse",
        "max_depth": 249,
        "min_samples_split": 5,
        "min_samples_leaf": 1,
        "ccp_alpha": 0.0385,
        "n_estimators": 173,
        "bootstrap": true,
        "max_samples": 1.0
    },
    "prune_testing_loss": {
        "criterion": "poisson",
        "max_depth": 245,
        "min_samples_split": 4,
        "min_samples_leaf": 1,
        "ccp_alpha": 0.0,
        "n_estimators": 275,
        "bootstrap": true,
        "max_samples": 0.78
    },
    "weight_normalisation_testing_loss": {
        "criterion": "absolute_error",
        "max_depth": 395,
        "min_samples_split": 2,
        "min_samples_leaf": 3,
        "ccp_alpha": 0.0,
        "n_estimators": 124,
        "bootstrap": true,
        "max_samples": 0.83
    }
}